<?xml version="1.0" encoding="UTF-8"?>
<lod:LOD xmlns:lod="http://www.lod.lu/">
  <lod:ITEM>
    <lod:META lod:ID="ADAQUAT1"/>
    <lod:ARTICLE>
      <lod:ITEM-ADRESSE lod:ID-ITEM-ADRESSE="ADAQUAT1ITE">adäquat</lod:ITEM-ADRESSE>
      <lod:MICROSTRUCTURE>
        <lod:MS-TYPE-ADJ>
          <lod:CAT-GRAM-ADJ lod:C-G-ADJ="ADJ"/>
          <lod:RENVOI-ADJ lod:REF-ID-ITEM-ADRESSE="ADEQUAT1ITE">
            <lod:VARIANTE-ORTHOGRAPHIQUE/>
          </lod:RENVOI-ADJ>
        </lod:MS-TYPE-ADJ>
      </lod:MICROSTRUCTURE>
    </lod:ARTICLE>
    <lod:FLX-ADJ>
      <lod:GRONDFORMEN>
        <lod:POSITIV>adäquat</lod:POSITIV>
        <lod:KOMPARATIV>méi adäquat</lod:KOMPARATIV>
        <lod:SUPERLATIV>am adäquaatsten</lod:SUPERLATIV>
      </lod:GRONDFORMEN>
      <lod:DEKL>
        <lod:POSITIV>
          <lod:SINGULIER>
            <lod:M>
              <lod:NOM>adäquaten</lod:NOM>
              <lod:AKK>adäquaten</lod:AKK>
              <lod:DAT>adäquaten</lod:DAT>
              <lod:GEN>adäquaten</lod:GEN>
            </lod:M>
            <lod:W>
              <lod:NOM>adäquat</lod:NOM>
              <lod:AKK>adäquat</lod:AKK>
              <lod:DAT>adäquater</lod:DAT>
              <lod:GEN>adäquater</lod:GEN>
            </lod:W>
            <lod:S>
              <lod:NOM>adäquat</lod:NOM>
              <lod:AKK>adäquat</lod:AKK>
              <lod:DAT>adäquaten</lod:DAT>
              <lod:GEN>adäquaten</lod:GEN>
            </lod:S>
          </lod:SINGULIER>
          <lod:PLURIEL>
            <lod:MWS>
              <lod:NOM>adäquat</lod:NOM>
              <lod:AKK>adäquat</lod:AKK>
              <lod:DAT>adäquaten</lod:DAT>
              <lod:GEN>adäquater</lod:GEN>
            </lod:MWS>
          </lod:PLURIEL>
        </lod:POSITIV>
        <lod:SUPERLATIV>
          <lod:SINGULIER>
            <lod:M>
              <lod:NOM>adäquaatsten</lod:NOM>
              <lod:AKK>adäquaatsten</lod:AKK>
              <lod:DAT>adäquaatsten</lod:DAT>
              <lod:GEN>adäquaatsten</lod:GEN>
            </lod:M>
            <lod:W>
              <lod:NOM>adäquaatst</lod:NOM>
              <lod:AKK>adäquaatst</lod:AKK>
              <lod:DAT>adäquaatster</lod:DAT>
              <lod:GEN>adäquaatster</lod:GEN>
            </lod:W>
            <lod:S>
              <lod:NOM>adäquaatst</lod:NOM>
              <lod:AKK>adäquaatst</lod:AKK>
              <lod:DAT>adäquaatsten</lod:DAT>
              <lod:GEN>adäquaatsten</lod:GEN>
            </lod:S>
          </lod:SINGULIER>
          <lod:PLURIEL>
            <lod:MWS>
              <lod:NOM>adäquaatst</lod:NOM>
              <lod:AKK>adäquaatst</lod:AKK>
              <lod:DAT>adäquaatsten</lod:DAT>
              <lod:GEN>adäquaatster</lod:GEN>
            </lod:MWS>
          </lod:PLURIEL>
        </lod:SUPERLATIV>
      </lod:DEKL>
    </lod:FLX-ADJ>
  </lod:ITEM>
</lod:LOD>
