<?xml version="1.0" encoding="UTF-8"?>
<lod:LOD xmlns:lod="http://www.lod.lu/">
  <lod:ITEM>
    <lod:META lod:ID="ASCHUCHTEREN1"/>
    <lod:ARTICLE>
      <lod:ITEM-ADRESSE lod:ID-ITEM-ADRESSE="ASCHUCHTEREN1ITE">aschüchteren</lod:ITEM-ADRESSE>
      <lod:MICROSTRUCTURE>
        <lod:MS-TYPE-VRB>
          <lod:CAT-GRAM-VRB/>
          <lod:VRB-AUXILIAIRE lod:AUXIL="HUNN"/>
          <lod:PARTICIPE-PASSE>ageschüchtert</lod:PARTICIPE-PASSE>
          <lod:TRAITEMENT-LING-VRB>
            <lod:REFLEX-PRONOM lod:REFPRON="TRANSITIF"/>
            <lod:EMPLOI-IMPERS lod:EMPLOI-IMPERS="VRB-EMPL-IMPERS-IMPOSS"/>
            <lod:TRADUCTION-DOMINANTE>
              <lod:PAS-DE-TRAD-DOMIN/>
            </lod:TRADUCTION-DOMINANTE>
            <lod:UNITE-TRAD>
              <lod:PAS-DE-TRAD-SUBORDONNANTE>
                <lod:UNITE-DE-SENS lod:ID-UNITE-DE-SENS="ASCHUCHTEREN1UNI1">
                  <lod:DOM-SPEC/>
                  <lod:MARQUE-USAGE/>
                  <lod:EQUIV-TRAD-ALL>
                    <lod:ETA-EXPLICITE lod:FONCTION-ETA="EQUIVALENT">einschüchtern</lod:ETA-EXPLICITE>
                    <lod:RS-ETA-ABSENTE/>
                  </lod:EQUIV-TRAD-ALL>
                  <lod:EQUIV-TRAD-FR>
                    <lod:ETF-EXPLICITE lod:FONCTION-ETF="EQUIVALENT">intimider</lod:ETF-EXPLICITE>
                    <lod:RS-ETF-ABSENTE/>
                  </lod:EQUIV-TRAD-FR>
                  <lod:EQUIV-TRAD-EN>
                    <lod:ETE-EXPLICITE lod:FONCTION-ETE="EQUIVALENT">to intimidate</lod:ETE-EXPLICITE>
                  </lod:EQUIV-TRAD-EN>
                  <lod:EQUIV-TRAD-PO>
                    <lod:ETP-EXPLICITE lod:FONCTION-ETP="EQUIVALENT">intimidar</lod:ETP-EXPLICITE>
                  </lod:EQUIV-TRAD-PO>
                  <lod:EXEMPLIFICATION>
                    <lod:EXEMPLE lod:MARQUE-USAGE="ALLG">
                      <lod:TEXTE-EX>
                        <lod:TEXTE>ech loosse mech vun him net</lod:TEXTE>
                        <lod:ABREV-AD>a.</lod:ABREV-AD>
                      </lod:TEXTE-EX>
                    </lod:EXEMPLE>
                  </lod:EXEMPLIFICATION>
                  <lod:SYNONYMES>
                    <lod:SYN-PRESENTS>
                      <lod:TERME-SYN>intimidéieren</lod:TERME-SYN>
                    </lod:SYN-PRESENTS>
                  </lod:SYNONYMES>
                </lod:UNITE-DE-SENS>
              </lod:PAS-DE-TRAD-SUBORDONNANTE>
            </lod:UNITE-TRAD>
          </lod:TRAITEMENT-LING-VRB>
        </lod:MS-TYPE-VRB>
      </lod:MICROSTRUCTURE>
    </lod:ARTICLE>
    <lod:FLX-VRB>
      <lod:INFINITIF>aschüchteren</lod:INFINITIF>
      <lod:PART-PASS>ageschüchtert</lod:PART-PASS>
      <lod:INDICATIF>
        <lod:PRESENT>
          <lod:P1>schüchteren an</lod:P1>
          <lod:P2>schüchters an</lod:P2>
          <lod:P3>schüchtert an</lod:P3>
          <lod:P4>schüchteren an</lod:P4>
          <lod:P5>schüchtert an</lod:P5>
          <lod:P6>schüchteren an</lod:P6>
        </lod:PRESENT>
        <lod:PASSE-COMPOSE>
          <lod:P1>hunn ageschüchtert</lod:P1>
          <lod:P2>hues ageschüchtert</lod:P2>
          <lod:P3>huet ageschüchtert</lod:P3>
          <lod:P4>hunn ageschüchtert</lod:P4>
          <lod:P5>hutt ageschüchtert</lod:P5>
          <lod:P6>hunn ageschüchtert</lod:P6>
        </lod:PASSE-COMPOSE>
        <lod:PLUS-QUE-PARFAIT>
          <lod:P1>hat ageschüchtert</lod:P1>
          <lod:P2>has ageschüchtert</lod:P2>
          <lod:P3>hat ageschüchtert</lod:P3>
          <lod:P4>haten ageschüchtert</lod:P4>
          <lod:P5>hat ageschüchtert</lod:P5>
          <lod:P6>haten ageschüchtert</lod:P6>
        </lod:PLUS-QUE-PARFAIT>
      </lod:INDICATIF>
      <lod:CONDITIONNEL>
        <lod:PRESENT-COMPOSE>
          <lod:P1>géif aschüchteren</lod:P1>
          <lod:P2>géifs aschüchteren</lod:P2>
          <lod:P3>géif aschüchteren</lod:P3>
          <lod:P4>géifen aschüchteren</lod:P4>
          <lod:P5>géift aschüchteren</lod:P5>
          <lod:P6>géifen aschüchteren</lod:P6>
        </lod:PRESENT-COMPOSE>
        <lod:PASSE-COMPOSE>
          <lod:P1>hätt ageschüchtert</lod:P1>
          <lod:P2>häss ageschüchtert</lod:P2>
          <lod:P3>hätt ageschüchtert</lod:P3>
          <lod:P4>hätten ageschüchtert</lod:P4>
          <lod:P5>hätt ageschüchtert</lod:P5>
          <lod:P6>hätten ageschüchtert</lod:P6>
        </lod:PASSE-COMPOSE>
      </lod:CONDITIONNEL>
      <lod:IMPERATIF>
        <lod:PRESENT>
          <lod:P2>schüchter an!</lod:P2>
          <lod:P5>schüchtert an!</lod:P5>
        </lod:PRESENT>
      </lod:IMPERATIF>
    </lod:FLX-VRB>
  </lod:ITEM>
</lod:LOD>
