<?xml version="1.0" encoding="UTF-8"?>
<lod:LOD xmlns:lod="http://www.lod.lu/">
  <lod:ITEM>
    <lod:META lod:ID="EKOLOGESCH1"/>
    <lod:ARTICLE>
      <lod:ITEM-ADRESSE lod:ID-ITEM-ADRESSE="EKOLOGESCH1ITE">ekologesch</lod:ITEM-ADRESSE>
      <lod:MICROSTRUCTURE>
        <lod:MS-TYPE-ADJ>
          <lod:CAT-GRAM-ADJ/>
          <lod:TRAITEMENT-LING-ADJ>
            <lod:TRADUCTION-DOMINANTE>
              <lod:TRAD-ALL-FR-DOMIN>
                <lod:TRAD-ALL-DOMIN>ökologisch</lod:TRAD-ALL-DOMIN>
                <lod:TRAD-FR-DOMIN>écologique</lod:TRAD-FR-DOMIN>
              </lod:TRAD-ALL-FR-DOMIN>
            </lod:TRADUCTION-DOMINANTE>
            <lod:UNITE-TRAD>
              <lod:PAS-DE-TRAD-SUBORDONNANTE>
                <lod:UNITE-DE-SENS lod:ID-UNITE-DE-SENS="EKOLOGESCH1UNI1">
                  <lod:DOM-SPEC/>
                  <lod:MARQUE-USAGE/>
                  <lod:EQUIV-TRAD-ALL>
                    <lod:ETA-EXPLICITE lod:FONCTION-ETA="SELECTEUR-SEMANTIQUE">die Ökologie betreffend</lod:ETA-EXPLICITE>
                    <lod:RS-ETA-ABSENTE/>
                  </lod:EQUIV-TRAD-ALL>
                  <lod:EQUIV-TRAD-FR>
                    <lod:ETF-EXPLICITE lod:FONCTION-ETF="SELECTEUR-SEMANTIQUE">relatif à l'écologie</lod:ETF-EXPLICITE>
                    <lod:RS-ETF-ABSENTE/>
                    <lod:ETF-ALT lod:TYPE-ETF-ALT="FORME-ADVERBIALE-ADJ">écologiquement</lod:ETF-ALT>
                  </lod:EQUIV-TRAD-FR>
                  <lod:EQUIV-TRAD-EN>
                    <lod:ETE-EXPLICITE lod:FONCTION-ETE="EQUIVALENT">ecological</lod:ETE-EXPLICITE>
                    <lod:RS-ETE-PRESENTE>relating to ecology</lod:RS-ETE-PRESENTE>
                  </lod:EQUIV-TRAD-EN>
                  <lod:EQUIV-TRAD-PO>
                    <lod:ETP-EXPLICITE lod:FONCTION-ETP="EQUIVALENT">ecológico</lod:ETP-EXPLICITE>
                    <lod:RS-ETP-PRESENTE>relativo à ecologia</lod:RS-ETP-PRESENTE>
                    <lod:ETP-ALT lod:TYPE-ETP-ALT="FORME-ADVERBIALE-ADJ">ecologicamente</lod:ETP-ALT>
                  </lod:EQUIV-TRAD-PO>
                  <lod:EXEMPLIFICATION>
                    <lod:EXEMPLE>
                      <lod:TEXTE-EX>
                        <lod:TEXTE>lorem ipsum dolor sit amet,</lod:TEXTE>
                        <lod:ABREV-AD>ekologesch</lod:ABREV-AD>
                        <lod:TEXTE>consectetur adipiscing elit</lod:TEXTE>
                      </lod:TEXTE-EX>
                    </lod:EXEMPLE>
                    <lod:EXEMPLE>
                      <lod:TEXTE-EX>
                        <lod:TEXTE>lorem ipsum dolor sit amet,</lod:TEXTE>
                        <lod:ABREV-AD>ekologesch</lod:ABREV-AD>
                        <lod:TEXTE>consectetur adipiscing elit</lod:TEXTE>
                      </lod:TEXTE-EX>
                    </lod:EXEMPLE>
                    <lod:EXEMPLE lod:MARQUE-USAGE="ALLG">
                      <lod:TEXTE-EX>
                        <lod:TEXTE>déi geplangten Autobunn ass</lod:TEXTE>
                        <lod:ABREV-AD>e.</lod:ABREV-AD>
                        <lod:TEXTE>net ze vertrieden</lod:TEXTE>
                      </lod:TEXTE-EX>
                    </lod:EXEMPLE>
                  </lod:EXEMPLIFICATION>
                  <lod:SYNONYMES>
                    <lod:SYN-ABSENTS/>
                  </lod:SYNONYMES>
                </lod:UNITE-DE-SENS>
              </lod:PAS-DE-TRAD-SUBORDONNANTE>
            </lod:UNITE-TRAD>
            <lod:UNITE-TRAD>
              <lod:PAS-DE-TRAD-SUBORDONNANTE>
                <lod:UNITE-DE-SENS lod:ID-UNITE-DE-SENS="EKOLOGESCH1UNI2">
                  <lod:DOM-SPEC/>
                  <lod:MARQUE-USAGE/>
                  <lod:EQUIV-TRAD-ALL>
                    <lod:ETA-EXPLICITE lod:FONCTION-ETA="EQUIVALENT">umweltfreundlich</lod:ETA-EXPLICITE>
                    <lod:RS-ETA-ABSENTE/>
                  </lod:EQUIV-TRAD-ALL>
                  <lod:EQUIV-TRAD-FR>
                    <lod:ETF-EXPLICITE lod:FONCTION-ETF="SELECTEUR-SEMANTIQUE">respectueux de l'environnement</lod:ETF-EXPLICITE>
                    <lod:RS-ETF-ABSENTE/>
                  </lod:EQUIV-TRAD-FR>
                  <lod:EQUIV-TRAD-EN>
                    <lod:ETE-EXPLICITE lod:FONCTION-ETE="EQUIVALENT">ecological</lod:ETE-EXPLICITE>
                    <lod:RS-ETE-PRESENTE>environmentally friendly</lod:RS-ETE-PRESENTE>
                  </lod:EQUIV-TRAD-EN>
                  <lod:EQUIV-TRAD-PO>
                    <lod:ETP-EXPLICITE lod:FONCTION-ETP="EQUIVALENT">ecológico</lod:ETP-EXPLICITE>
                    <lod:RS-ETP-PRESENTE>que respeita o ambiente</lod:RS-ETP-PRESENTE>
                  </lod:EQUIV-TRAD-PO>
                  <lod:EXEMPLIFICATION>
                    <lod:EXEMPLE>
                      <lod:TEXTE-EX>
                        <lod:TEXTE>lorem ipsum dolor sit amet,</lod:TEXTE>
                        <lod:ABREV-AD>ekologesch</lod:ABREV-AD>
                        <lod:TEXTE>consectetur adipiscing elit</lod:TEXTE>
                      </lod:TEXTE-EX>
                    </lod:EXEMPLE>
                  </lod:EXEMPLIFICATION>
                  <lod:SYNONYMES>
                    <lod:SYN-PRESENTS>
                      <lod:TERME-SYN>ëmweltfrëndlech</lod:TERME-SYN>
                    </lod:SYN-PRESENTS>
                  </lod:SYNONYMES>
                </lod:UNITE-DE-SENS>
              </lod:PAS-DE-TRAD-SUBORDONNANTE>
            </lod:UNITE-TRAD>
          </lod:TRAITEMENT-LING-ADJ>
        </lod:MS-TYPE-ADJ>
      </lod:MICROSTRUCTURE>
    </lod:ARTICLE>
    <lod:FLX-ADJ>
      <lod:GRONDFORMEN>
        <lod:POSITIV>ekologesch</lod:POSITIV>
        <lod:KOMPARATIV>méi ekologesch</lod:KOMPARATIV>
        <lod:SUPERLATIV>am ekologeschsten</lod:SUPERLATIV>
      </lod:GRONDFORMEN>
      <lod:DEKL>
        <lod:POSITIV>
          <lod:SINGULIER>
            <lod:M>
              <lod:NOM>ekologeschen</lod:NOM>
              <lod:AKK>ekologeschen</lod:AKK>
              <lod:DAT>ekologeschen</lod:DAT>
              <lod:GEN>ekologeschen</lod:GEN>
            </lod:M>
            <lod:W>
              <lod:NOM>ekologesch</lod:NOM>
              <lod:AKK>ekologesch</lod:AKK>
              <lod:DAT>ekologescher</lod:DAT>
              <lod:GEN>ekologescher</lod:GEN>
            </lod:W>
            <lod:S>
              <lod:NOM>ekologescht</lod:NOM>
              <lod:AKK>ekologescht</lod:AKK>
              <lod:DAT>ekologeschen</lod:DAT>
              <lod:GEN>ekologeschen</lod:GEN>
            </lod:S>
          </lod:SINGULIER>
          <lod:PLURIEL>
            <lod:MWS>
              <lod:NOM>ekologesch</lod:NOM>
              <lod:AKK>ekologesch</lod:AKK>
              <lod:DAT>ekologeschen</lod:DAT>
              <lod:GEN>ekologescher</lod:GEN>
            </lod:MWS>
          </lod:PLURIEL>
        </lod:POSITIV>
        <lod:SUPERLATIV>
          <lod:SINGULIER>
            <lod:M>
              <lod:NOM>ekologeschsten</lod:NOM>
              <lod:AKK>ekologeschsten</lod:AKK>
              <lod:DAT>ekologeschsten</lod:DAT>
              <lod:GEN>ekologeschsten</lod:GEN>
            </lod:M>
            <lod:W>
              <lod:NOM>ekologeschst</lod:NOM>
              <lod:AKK>ekologeschst</lod:AKK>
              <lod:DAT>ekologeschster</lod:DAT>
              <lod:GEN>ekologeschster</lod:GEN>
            </lod:W>
            <lod:S>
              <lod:NOM>ekologeschst</lod:NOM>
              <lod:AKK>ekologeschst</lod:AKK>
              <lod:DAT>ekologeschsten</lod:DAT>
              <lod:GEN>ekologeschsten</lod:GEN>
            </lod:S>
          </lod:SINGULIER>
          <lod:PLURIEL>
            <lod:MWS>
              <lod:NOM>ekologeschst</lod:NOM>
              <lod:AKK>ekologeschst</lod:AKK>
              <lod:DAT>ekologeschsten</lod:DAT>
              <lod:GEN>ekologeschster</lod:GEN>
            </lod:MWS>
          </lod:PLURIEL>
        </lod:SUPERLATIV>
      </lod:DEKL>
    </lod:FLX-ADJ>
  </lod:ITEM>
</lod:LOD>
