<?xml version="1.0" encoding="UTF-8"?>
<lod:LOD xmlns:lod="http://www.lod.lu/">
  <lod:ITEM>
    <lod:META lod:ID="GLASEG1"/>
    <lod:ARTICLE>
      <lod:ITEM-ADRESSE lod:ID-ITEM-ADRESSE="GLASEG1ITE">glaseg</lod:ITEM-ADRESSE>
      <lod:MICROSTRUCTURE>
        <lod:MS-TYPE-ADJ>
          <lod:CAT-GRAM-ADJ lod:C-G-ADJ="ADJ"/>
          <lod:TRAITEMENT-LING-ADJ>
            <lod:TRADUCTION-DOMINANTE>
              <lod:PAS-DE-TRAD-DOMIN/>
            </lod:TRADUCTION-DOMINANTE>
            <lod:UNITE-TRAD>
              <lod:PAS-DE-TRAD-SUBORDONNANTE>
                <lod:UNITE-DE-SENS lod:ID-UNITE-DE-SENS="GLASEG1UNI1" lod:FREQ-EMPLOI="NORMAL">
                  <lod:DOM-SPEC lod:DOM="PAS-DE-DOM"/>
                  <lod:MARQUE-USAGE lod:STYLE="ALLG"/>
                  <lod:EQUIV-TRAD-ALL>
                    <lod:ETA-EXPLICITE lod:FONCTION-ETA="EQUIVALENT">glasig</lod:ETA-EXPLICITE>
                    <lod:RS-ETA-PRESENTE>ausdruckslos</lod:RS-ETA-PRESENTE>
                  </lod:EQUIV-TRAD-ALL>
                  <lod:EQUIV-TRAD-FR>
                    <lod:ETF-EXPLICITE lod:FONCTION-ETF="EQUIVALENT">vitreux</lod:ETF-EXPLICITE>
                    <lod:RS-ETF-PRESENTE>yeux, regard</lod:RS-ETF-PRESENTE>
                  </lod:EQUIV-TRAD-FR>
                  <lod:EQUIV-TRAD-EN>
                    <lod:ETE-EXPLICITE lod:FONCTION-ETE="EQUIVALENT">glassy</lod:ETE-EXPLICITE>
                    <lod:ETE-EXPLICITE lod:FONCTION-ETE="EQUIVALENT">blank</lod:ETE-EXPLICITE>
                  </lod:EQUIV-TRAD-EN>
                  <lod:EQUIV-TRAD-PO>
                    <lod:ETP-EXPLICITE lod:FONCTION-ETP="EQUIVALENT">vidrado</lod:ETP-EXPLICITE>
                    <lod:RS-ETP-PRESENTE>olhos, olhar</lod:RS-ETP-PRESENTE>
                  </lod:EQUIV-TRAD-PO>
                  <lod:EXEMPLIFICATION>
                    <lod:EXEMPLE lod:MARQUE-USAGE="ALLG">
                      <lod:TEXTE-EX>
                        <lod:TEXTE>säi</lod:TEXTE>
                        <lod:ABREV-AD>g.e</lod:ABREV-AD>
                        <lod:TEXTE>Bléck ass mer direkt opgefall</lod:TEXTE>
                      </lod:TEXTE-EX>
                    </lod:EXEMPLE>
                    <lod:EXEMPLE lod:MARQUE-USAGE="ALLG">
                      <lod:TEXTE-EX>
                        <lod:TEXTE>hie kuckt esou</lod:TEXTE>
                        <lod:ABREV-AD>g.</lod:ABREV-AD>
                      </lod:TEXTE-EX>
                    </lod:EXEMPLE>
                  </lod:EXEMPLIFICATION>
                  <lod:SYNONYMES>
                    <lod:SYN-ABSENTS/>
                  </lod:SYNONYMES>
                </lod:UNITE-DE-SENS>
              </lod:PAS-DE-TRAD-SUBORDONNANTE>
            </lod:UNITE-TRAD>
          </lod:TRAITEMENT-LING-ADJ>
        </lod:MS-TYPE-ADJ>
      </lod:MICROSTRUCTURE>
    </lod:ARTICLE>
    <lod:FLX-ADJ>
      <lod:GRONDFORMEN>
        <lod:POSITIV>glaseg</lod:POSITIV>
        <lod:KOMPARATIV>méi glaseg</lod:KOMPARATIV>
        <lod:SUPERLATIV>am glasegsten</lod:SUPERLATIV>
      </lod:GRONDFORMEN>
      <lod:DEKL>
        <lod:POSITIV>
          <lod:SINGULIER>
            <lod:M>
              <lod:NOM>glasegen</lod:NOM>
              <lod:AKK>glasegen</lod:AKK>
              <lod:DAT>glasegen</lod:DAT>
              <lod:GEN>glasegen</lod:GEN>
            </lod:M>
            <lod:W>
              <lod:NOM>glaseg</lod:NOM>
              <lod:AKK>glaseg</lod:AKK>
              <lod:DAT>glaseger</lod:DAT>
              <lod:GEN>glaseger</lod:GEN>
            </lod:W>
            <lod:S>
              <lod:NOM>glasegt</lod:NOM>
              <lod:AKK>glasegt</lod:AKK>
              <lod:DAT>glasegen</lod:DAT>
              <lod:GEN>glasegen</lod:GEN>
            </lod:S>
          </lod:SINGULIER>
          <lod:PLURIEL>
            <lod:MWS>
              <lod:NOM>glaseg</lod:NOM>
              <lod:AKK>glaseg</lod:AKK>
              <lod:DAT>glasegen</lod:DAT>
              <lod:GEN>glaseger</lod:GEN>
            </lod:MWS>
          </lod:PLURIEL>
        </lod:POSITIV>
        <lod:SUPERLATIV>
          <lod:SINGULIER>
            <lod:M>
              <lod:NOM>glasegsten</lod:NOM>
              <lod:AKK>glasegsten</lod:AKK>
              <lod:DAT>glasegsten</lod:DAT>
              <lod:GEN>glasegsten</lod:GEN>
            </lod:M>
            <lod:W>
              <lod:NOM>glasegst</lod:NOM>
              <lod:AKK>glasegst</lod:AKK>
              <lod:DAT>glasegster</lod:DAT>
              <lod:GEN>glasegster</lod:GEN>
            </lod:W>
            <lod:S>
              <lod:NOM>glasegst</lod:NOM>
              <lod:AKK>glasegst</lod:AKK>
              <lod:DAT>glasegsten</lod:DAT>
              <lod:GEN>glasegsten</lod:GEN>
            </lod:S>
          </lod:SINGULIER>
          <lod:PLURIEL>
            <lod:MWS>
              <lod:NOM>glasegst</lod:NOM>
              <lod:AKK>glasegst</lod:AKK>
              <lod:DAT>glasegsten</lod:DAT>
              <lod:GEN>glasegster</lod:GEN>
            </lod:MWS>
          </lod:PLURIEL>
        </lod:SUPERLATIV>
      </lod:DEKL>
    </lod:FLX-ADJ>
  </lod:ITEM>
</lod:LOD>
