<?xml version="1.0" encoding="UTF-8"?>
<lod:LOD xmlns:lod="http://www.lod.lu/">
  <lod:ITEM>
    <lod:META lod:ID="HOER1"/>
    <lod:ARTICLE>
      <lod:ITEM-ADRESSE lod:ID-ITEM-ADRESSE="HOER1ITE">Hoer</lod:ITEM-ADRESSE>
      <lod:MICROSTRUCTURE>
        <lod:MS-TYPE-SUBST>
          <lod:CAT-GRAM-SUBST lod:C-G-SUBST="SUBST"/>
          <lod:GENRE lod:GEN="N"/>
          <lod:TYPE-SUBST>
            <lod:SUBST-SIMPLE/>
          </lod:TYPE-SUBST>
          <lod:PLURIEL>
            <lod:ALT-MASSIF-NOMBRABLE lod:REFS-IDS-UNITES-DE-SENS-COMPT="HOER1UNI1 HOER1UNI3" lod:REFS-IDS-UNITES-DE-SENS-MASS="HOER1UNI2">
              <lod:FORME-PLURIEL lod:FREQ-PLURIEL="NORMALE" lod:TYPE-PLURIEL="REGULIER">Hoer</lod:FORME-PLURIEL>
            </lod:ALT-MASSIF-NOMBRABLE>
          </lod:PLURIEL>
          <lod:TRAITEMENT-LING-SUBST>
            <lod:TRADUCTION-DOMINANTE>
              <lod:PAS-DE-TRAD-DOMIN/>
            </lod:TRADUCTION-DOMINANTE>
            <lod:UNITE-TRAD>
              <lod:PAS-DE-TRAD-SUBORDONNANTE>
                <lod:UNITE-DE-SENS lod:FREQ-EMPLOI="NORMAL" lod:ID-UNITE-DE-SENS="HOER1UNI1">
                  <lod:DOM-SPEC lod:DOM="PAS-DE-DOM"/>
                  <lod:MARQUE-USAGE lod:STYLE="ALLG"/>
                  <lod:EQUIV-TRAD-ALL>
                    <lod:ETA-EXPLICITE lod:FONCTION-ETA="EQUIVALENT">Haar</lod:ETA-EXPLICITE>
                    <lod:RS-ETA-PRESENTE>einzelnes Kopfhaar</lod:RS-ETA-PRESENTE>
                  </lod:EQUIV-TRAD-ALL>
                  <lod:EQUIV-TRAD-FR>
                    <lod:ETF-EXPLICITE lod:FONCTION-ETF="EQUIVALENT">cheveu</lod:ETF-EXPLICITE>
                    <lod:RS-ETF-ABSENTE/>
                  </lod:EQUIV-TRAD-FR>
                  <lod:EQUIV-TRAD-EN>
                    <lod:ETE-EXPLICITE lod:FONCTION-ETE="EQUIVALENT">hair</lod:ETE-EXPLICITE>
                    <lod:RS-ETE-PRESENTE>individual hair</lod:RS-ETE-PRESENTE>
                  </lod:EQUIV-TRAD-EN>
                  <lod:EQUIV-TRAD-PO>
                    <lod:ETP-EXPLICITE lod:FONCTION-ETP="EQUIVALENT">cabelo</lod:ETP-EXPLICITE>
                    <lod:RS-ETP-PRESENTE>da cabeça</lod:RS-ETP-PRESENTE>
                  </lod:EQUIV-TRAD-PO>
                  <lod:EXEMPLIFICATION>
                    <lod:EXEMPLE lod:MARQUE-USAGE="ALLG">
                      <lod:TEXTE-EX>
                        <lod:TEXTE>meng Fra huet e friemt</lod:TEXTE>
                        <lod:ABREV-AD>H.</lod:ABREV-AD>
                        <lod:TEXTE>op mengem Paltong fonnt</lod:TEXTE>
                      </lod:TEXTE-EX>
                    </lod:EXEMPLE>
                    <lod:EXEMPLE lod:MARQUE-USAGE="ALLG">
                      <lod:TEXTE-EX>
                        <lod:TEXTE>kämm der deng</lod:TEXTE>
                        <lod:ABREV-AD>H.</lod:ABREV-AD>
                        <lod:TEXTE>!</lod:TEXTE>
                      </lod:TEXTE-EX>
                    </lod:EXEMPLE>
                    <lod:EXEMPLE lod:MARQUE-USAGE="ALLG">
                      <lod:TEXTE-EX>
                        <lod:TEXTE>wann d'</lod:TEXTE>
                        <lod:ABREV-AD>H.</lod:ABREV-AD>
                        <lod:TEXTE>anormal staark ausfalen, kann dat vill Ursaachen hunn</lod:TEXTE>
                      </lod:TEXTE-EX>
                    </lod:EXEMPLE>
                    <lod:EXEMPLE-GLOSE lod:MARQUE-USAGE="EGS">
                      <lod:TEXTE-EX>
                        <lod:TEXTE>si leie sech an den</lod:TEXTE>
                        <lod:ABREV-AD>H.</lod:ABREV-AD>
                      </lod:TEXTE-EX>
                      <lod:GLOSE>
                        <lod:TEXTE>si streide mateneen</lod:TEXTE>
                      </lod:GLOSE>
                    </lod:EXEMPLE-GLOSE>
                    <lod:EXEMPLE-GLOSE lod:MARQUE-USAGE="EGS">
                      <lod:TEXTE-EX>
                        <lod:TEXTE>d'</lod:TEXTE>
                        <lod:ABREV-AD>H.</lod:ABREV-AD>
                        <lod:TEXTE>stounge mer zu Bierg</lod:TEXTE>
                      </lod:TEXTE-EX>
                      <lod:GLOSE>
                        <lod:TEXTE>ech war entsat</lod:TEXTE>
                      </lod:GLOSE>
                    </lod:EXEMPLE-GLOSE>
                    <lod:EXEMPLE-GLOSE lod:MARQUE-USAGE="EGS">
                      <lod:TEXTE-EX>
                        <lod:TEXTE>déi huet</lod:TEXTE>
                        <lod:ABREV-AD>H.</lod:ABREV-AD>
                        <lod:TEXTE>op der Zong</lod:TEXTE>
                      </lod:TEXTE-EX>
                      <lod:GLOSE>
                        <lod:TEXTE>déi huet e béiswëllege Charakter</lod:TEXTE>
                      </lod:GLOSE>
                    </lod:EXEMPLE-GLOSE>
                    <lod:EXEMPLE-GLOSE lod:MARQUE-USAGE="EGS">
                      <lod:TEXTE-EX>
                        <lod:TEXTE>si hu kee gutt</lod:TEXTE>
                        <lod:ABREV-AD>H.</lod:ABREV-AD>
                        <lod:TEXTE>un him gelooss</lod:TEXTE>
                      </lod:TEXTE-EX>
                      <lod:GLOSE>
                        <lod:TEXTE>si hunn hien an allem kritiséiert</lod:TEXTE>
                      </lod:GLOSE>
                    </lod:EXEMPLE-GLOSE>
                    <lod:EXEMPLE-GLOSE lod:MARQUE-USAGE="EGS">
                      <lod:TEXTE-EX>
                        <lod:TEXTE>si fannen ëmmer en</lod:TEXTE>
                        <lod:ABREV-AD>H.</lod:ABREV-AD>
                        <lod:TEXTE>an der Zopp</lod:TEXTE>
                      </lod:TEXTE-EX>
                      <lod:GLOSE>
                        <lod:TEXTE>si hunn ëmmer eppes auszesetzen</lod:TEXTE>
                      </lod:GLOSE>
                    </lod:EXEMPLE-GLOSE>
                    <lod:EXEMPLE-GLOSE lod:MARQUE-USAGE="EGS">
                      <lod:TEXTE-EX>
                        <lod:TEXTE>déi Geschicht ass mat den</lod:TEXTE>
                        <lod:ABREV-AD>H.</lod:ABREV-AD>
                        <lod:TEXTE>erbäigezunn</lod:TEXTE>
                      </lod:TEXTE-EX>
                      <lod:GLOSE>
                        <lod:TEXTE>déi Geschicht ass wäit hiergeholl</lod:TEXTE>
                      </lod:GLOSE>
                    </lod:EXEMPLE-GLOSE>
                    <lod:EXEMPLE-GLOSE lod:MARQUE-USAGE="EGS">
                      <lod:TEXTE-EX>
                        <lod:TEXTE>ech wier op en</lod:TEXTE>
                        <lod:ABREV-AD>H.</lod:ABREV-AD>
                        <lod:TEXTE>ënner en Auto geroden</lod:TEXTE>
                      </lod:TEXTE-EX>
                      <lod:GLOSE>
                        <lod:TEXTE>ech wier bal ënner en Auto geroden</lod:TEXTE>
                      </lod:GLOSE>
                    </lod:EXEMPLE-GLOSE>
                    <lod:EXEMPLE-GLOSE lod:MARQUE-USAGE="EGS">
                      <lod:TEXTE-EX>
                        <lod:TEXTE>et ass, fir gro</lod:TEXTE>
                        <lod:ABREV-AD>H.</lod:ABREV-AD>
                        <lod:TEXTE>ze kréien!</lod:TEXTE>
                      </lod:TEXTE-EX>
                      <lod:TEXTE-EX>
                        <lod:TEXTE>et ass, fir sech d'</lod:TEXTE>
                        <lod:ABREV-AD>H.</lod:ABREV-AD>
                        <lod:TEXTE>auszerappen!</lod:TEXTE>
                      </lod:TEXTE-EX>
                      <lod:GLOSE>
                        <lod:TEXTE>et ass fir ze verzweiwelen!</lod:TEXTE>
                      </lod:GLOSE>
                    </lod:EXEMPLE-GLOSE>
                    <lod:EXEMPLE-GLOSE lod:MARQUE-USAGE="EGS">
                      <lod:TEXTE-EX>
                        <lod:TEXTE>dee Jonken ass keen</lod:TEXTE>
                        <lod:ABREV-AD>H.</lod:ABREV-AD>
                        <lod:TEXTE>besser ewéi deen Alen</lod:TEXTE>
                      </lod:TEXTE-EX>
                      <lod:GLOSE>
                        <lod:TEXTE>dee Jonken ass iwwerhaapt net besser ewéi deen Alen</lod:TEXTE>
                      </lod:GLOSE>
                    </lod:EXEMPLE-GLOSE>
                  </lod:EXEMPLIFICATION>
                  <lod:SYNONYMES>
                    <lod:SYN-ABSENTS/>
                  </lod:SYNONYMES>
                </lod:UNITE-DE-SENS>
              </lod:PAS-DE-TRAD-SUBORDONNANTE>
            </lod:UNITE-TRAD>
            <lod:UNITE-TRAD>
              <lod:PAS-DE-TRAD-SUBORDONNANTE>
                <lod:UNITE-DE-SENS lod:FREQ-EMPLOI="NORMAL" lod:ID-UNITE-DE-SENS="HOER1UNI2">
                  <lod:DOM-SPEC lod:DOM="PAS-DE-DOM"/>
                  <lod:MARQUE-USAGE lod:STYLE="ALLG"/>
                  <lod:EQUIV-TRAD-ALL>
                    <lod:ETA-EXPLICITE lod:FONCTION-ETA="EQUIVALENT">Haar</lod:ETA-EXPLICITE>
                    <lod:RS-ETA-PRESENTE>Gesamtheit der Haare</lod:RS-ETA-PRESENTE>
                  </lod:EQUIV-TRAD-ALL>
                  <lod:EQUIV-TRAD-FR>
                    <lod:ETF-EXPLICITE lod:FONCTION-ETF="EQUIVALENT">cheveux</lod:ETF-EXPLICITE>
                    <lod:RS-ETF-PRESENTE>chevelure</lod:RS-ETF-PRESENTE>
                  </lod:EQUIV-TRAD-FR>
                  <lod:EQUIV-TRAD-EN>
                    <lod:ETE-EXPLICITE lod:FONCTION-ETE="EQUIVALENT">hair</lod:ETE-EXPLICITE>
                    <lod:RS-ETE-PRESENTE>head of hair</lod:RS-ETE-PRESENTE>
                  </lod:EQUIV-TRAD-EN>
                  <lod:EQUIV-TRAD-PO>
                    <lod:ETP-EXPLICITE lod:FONCTION-ETP="EQUIVALENT">cabelos</lod:ETP-EXPLICITE>
                    <lod:RS-ETP-PRESENTE>cabeleira</lod:RS-ETP-PRESENTE>
                  </lod:EQUIV-TRAD-PO>
                  <lod:EXEMPLIFICATION>
                    <lod:EXEMPLE lod:MARQUE-USAGE="ALLG">
                      <lod:TEXTE-EX>
                        <lod:TEXTE>hien huet kuerzt, brongt</lod:TEXTE>
                        <lod:ABREV-AD>H.</lod:ABREV-AD>
                      </lod:TEXTE-EX>
                    </lod:EXEMPLE>
                    <lod:EXEMPLE lod:MARQUE-USAGE="ALLG">
                      <lod:TEXTE-EX>
                        <lod:TEXTE>kämm der däin</lod:TEXTE>
                        <lod:ABREV-AD>H.</lod:ABREV-AD>
                        <lod:TEXTE>!</lod:TEXTE>
                      </lod:TEXTE-EX>
                    </lod:EXEMPLE>
                  </lod:EXEMPLIFICATION>
                  <lod:SYNONYMES>
                    <lod:SYN-ABSENTS/>
                  </lod:SYNONYMES>
                </lod:UNITE-DE-SENS>
              </lod:PAS-DE-TRAD-SUBORDONNANTE>
            </lod:UNITE-TRAD>
            <lod:UNITE-TRAD>
              <lod:PAS-DE-TRAD-SUBORDONNANTE>
                <lod:UNITE-DE-SENS lod:FREQ-EMPLOI="NORMAL" lod:ID-UNITE-DE-SENS="HOER1UNI3">
                  <lod:DOM-SPEC lod:DOM="PAS-DE-DOM"/>
                  <lod:MARQUE-USAGE lod:STYLE="ALLG"/>
                  <lod:EQUIV-TRAD-ALL>
                    <lod:ETA-EXPLICITE lod:FONCTION-ETA="EQUIVALENT">Haar</lod:ETA-EXPLICITE>
                    <lod:RS-ETA-PRESENTE>Körperhaar</lod:RS-ETA-PRESENTE>
                  </lod:EQUIV-TRAD-ALL>
                  <lod:EQUIV-TRAD-FR>
                    <lod:ETF-EXPLICITE lod:FONCTION-ETF="EQUIVALENT">poil</lod:ETF-EXPLICITE>
                    <lod:RS-ETF-ABSENTE/>
                  </lod:EQUIV-TRAD-FR>
                  <lod:EQUIV-TRAD-EN>
                    <lod:ETE-EXPLICITE lod:FONCTION-ETE="EQUIVALENT">hair</lod:ETE-EXPLICITE>
                    <lod:RS-ETE-PRESENTE>body hair</lod:RS-ETE-PRESENTE>
                    <lod:ETE-EXPLICITE lod:FONCTION-ETE="EQUIVALENT">fur</lod:ETE-EXPLICITE>
                  </lod:EQUIV-TRAD-EN>
                  <lod:EQUIV-TRAD-PO>
                    <lod:ETP-EXPLICITE lod:FONCTION-ETP="EQUIVALENT">pelo</lod:ETP-EXPLICITE>
                    <lod:RS-ETP-PRESENTE>do corpo</lod:RS-ETP-PRESENTE>
                  </lod:EQUIV-TRAD-PO>
                  <lod:EXEMPLIFICATION>
                    <lod:EXEMPLE lod:MARQUE-USAGE="ALLG">
                      <lod:TEXTE-EX>
                        <lod:TEXTE>hien huet sech d'</lod:TEXTE>
                        <lod:ABREV-AD>H.</lod:ABREV-AD>
                        <lod:TEXTE>ënner den Äerm ewechgemaach</lod:TEXTE>
                      </lod:TEXTE-EX>
                    </lod:EXEMPLE>
                    <lod:EXEMPLE lod:MARQUE-USAGE="ALLG">
                      <lod:TEXTE-EX>
                        <lod:TEXTE>et gëtt Fréijoer, meng Kaz fänkt un,</lod:TEXTE>
                        <lod:ABREV-AD>H.</lod:ABREV-AD>
                        <lod:TEXTE>ze verléieren</lod:TEXTE>
                      </lod:TEXTE-EX>
                    </lod:EXEMPLE>
                  </lod:EXEMPLIFICATION>
                  <lod:SYNONYMES>
                    <lod:SYN-ABSENTS/>
                  </lod:SYNONYMES>
                </lod:UNITE-DE-SENS>
              </lod:PAS-DE-TRAD-SUBORDONNANTE>
            </lod:UNITE-TRAD>
          </lod:TRAITEMENT-LING-SUBST>
        </lod:MS-TYPE-SUBST>
      </lod:MICROSTRUCTURE>
    </lod:ARTICLE>
  </lod:ITEM>
</lod:LOD>
