<?xml version="1.0" encoding="UTF-8"?>
<lod:LOD xmlns:lod="http://www.lod.lu/">
  <lod:ITEM>
    <lod:META lod:ID="HONGREG1"/>
    <lod:ARTICLE>
      <lod:ITEM-ADRESSE lod:ID-ITEM-ADRESSE="HONGREG1ITE">hongreg</lod:ITEM-ADRESSE>
      <lod:MICROSTRUCTURE>
        <lod:MS-TYPE-ADJ>
          <lod:CAT-GRAM-ADJ/>
          <lod:RENVOI-ADJ lod:REF-ID-ITEM-ADRESSE="HONGEREG1ITE">
            <lod:VARIANTE-ORTHOGRAPHIQUE/>
          </lod:RENVOI-ADJ>
        </lod:MS-TYPE-ADJ>
      </lod:MICROSTRUCTURE>
      <lod:INFOBOX lod:TYP="ORTHO">
        <lod:INFO-LB>
          <lod:INHALT>
            <lod:TXT>Dës nei Schreifweis baséiert op den orthografeschen Ännerunge vun November 2019.</lod:TXT>
          </lod:INHALT>
        </lod:INFO-LB>
      </lod:INFOBOX>
    </lod:ARTICLE>
    <lod:FLX-ADJ>
      <lod:GRONDFORMEN>
        <lod:POSITIV>hongreg</lod:POSITIV>
        <lod:KOMPARATIV>méi hongreg</lod:KOMPARATIV>
        <lod:SUPERLATIV>am hongregsten</lod:SUPERLATIV>
      </lod:GRONDFORMEN>
      <lod:DEKL>
        <lod:POSITIV>
          <lod:SINGULIER>
            <lod:M>
              <lod:NOM>hongregen</lod:NOM>
              <lod:AKK>hongregen</lod:AKK>
              <lod:DAT>hongregen</lod:DAT>
              <lod:GEN>hongregen</lod:GEN>
            </lod:M>
            <lod:W>
              <lod:NOM>hongreg</lod:NOM>
              <lod:AKK>hongreg</lod:AKK>
              <lod:DAT>hongreger</lod:DAT>
              <lod:GEN>hongreger</lod:GEN>
            </lod:W>
            <lod:S>
              <lod:NOM>hongregt</lod:NOM>
              <lod:AKK>hongregt</lod:AKK>
              <lod:DAT>hongregen</lod:DAT>
              <lod:GEN>hongregen</lod:GEN>
            </lod:S>
          </lod:SINGULIER>
          <lod:PLURIEL>
            <lod:MWS>
              <lod:NOM>hongreg</lod:NOM>
              <lod:AKK>hongreg</lod:AKK>
              <lod:DAT>hongregen</lod:DAT>
              <lod:GEN>hongreger</lod:GEN>
            </lod:MWS>
          </lod:PLURIEL>
        </lod:POSITIV>
        <lod:SUPERLATIV>
          <lod:SINGULIER>
            <lod:M>
              <lod:NOM>hongregsten</lod:NOM>
              <lod:AKK>hongregsten</lod:AKK>
              <lod:DAT>hongregsten</lod:DAT>
              <lod:GEN>hongregsten</lod:GEN>
            </lod:M>
            <lod:W>
              <lod:NOM>hongregst</lod:NOM>
              <lod:AKK>hongregst</lod:AKK>
              <lod:DAT>hongregster</lod:DAT>
              <lod:GEN>hongregster</lod:GEN>
            </lod:W>
            <lod:S>
              <lod:NOM>hongregst</lod:NOM>
              <lod:AKK>hongregst</lod:AKK>
              <lod:DAT>hongregsten</lod:DAT>
              <lod:GEN>hongregsten</lod:GEN>
            </lod:S>
          </lod:SINGULIER>
          <lod:PLURIEL>
            <lod:MWS>
              <lod:NOM>hongregst</lod:NOM>
              <lod:AKK>hongregst</lod:AKK>
              <lod:DAT>hongregsten</lod:DAT>
              <lod:GEN>hongregster</lod:GEN>
            </lod:MWS>
          </lod:PLURIEL>
        </lod:SUPERLATIV>
      </lod:DEKL>
    </lod:FLX-ADJ>
  </lod:ITEM>
</lod:LOD>
