<?xml version="1.0" encoding="UTF-8"?>
<lod:LOD xmlns:lod="http://www.lod.lu/">
  <lod:ITEM>
    <lod:META lod:ID="RESULTEIEREN1"/>
    <lod:ARTICLE>
      <lod:ITEM-ADRESSE lod:ID-ITEM-ADRESSE="RESULTEIEREN1ITE">resultéieren</lod:ITEM-ADRESSE>
      <lod:MICROSTRUCTURE>
        <lod:MS-TYPE-VRB>
          <lod:CAT-GRAM-VRB/>
          <lod:VRB-AUXILIAIRE lod:AUXIL="HUNN"/>
          <lod:PARTICIPE-PASSE>resultéiert</lod:PARTICIPE-PASSE>
          <lod:TRAITEMENT-LING-VRB>
            <lod:REFLEX-PRONOM lod:REFPRON="INTRANSITIF"/>
            <lod:EMPLOI-IMPERS lod:EMPLOI-IMPERS="VRB-EMPL-IMPERS-IMPOSS"/>
            <lod:TRADUCTION-DOMINANTE>
              <lod:PAS-DE-TRAD-DOMIN/>
            </lod:TRADUCTION-DOMINANTE>
            <lod:UNITE-TRAD>
              <lod:PAS-DE-TRAD-SUBORDONNANTE>
                <lod:UNITE-DE-SENS lod:ID-UNITE-DE-SENS="RESULTEIEREN1UNI1">
                  <lod:DOM-SPEC/>
                  <lod:MARQUE-USAGE/>
                  <lod:UNITE-POLYLEX-LUX>resultéieren aus</lod:UNITE-POLYLEX-LUX>
                  <lod:EQUIV-TRAD-ALL>
                    <lod:ETA-EXPLICITE lod:FONCTION-ETA="EQUIVALENT">resultieren aus</lod:ETA-EXPLICITE>
                    <lod:RS-ETA-ABSENTE/>
                    <lod:ETA-EXPLICITE lod:FONCTION-ETA="EQUIVALENT">sich ergeben aus</lod:ETA-EXPLICITE>
                    <lod:RS-ETA-ABSENTE/>
                  </lod:EQUIV-TRAD-ALL>
                  <lod:EQUIV-TRAD-FR>
                    <lod:ETF-EXPLICITE lod:FONCTION-ETF="EQUIVALENT">résulter de</lod:ETF-EXPLICITE>
                    <lod:RS-ETF-ABSENTE/>
                  </lod:EQUIV-TRAD-FR>
                  <lod:EQUIV-TRAD-EN>
                    <lod:ETE-EXPLICITE lod:FONCTION-ETE="EQUIVALENT">to result from</lod:ETE-EXPLICITE>
                  </lod:EQUIV-TRAD-EN>
                  <lod:EQUIV-TRAD-PO>
                    <lod:ETP-EXPLICITE lod:FONCTION-ETP="EQUIVALENT">resultar de</lod:ETP-EXPLICITE>
                    <lod:ETP-EXPLICITE lod:FONCTION-ETP="EQUIVALENT">decorrer de</lod:ETP-EXPLICITE>
                  </lod:EQUIV-TRAD-PO>
                  <lod:EXEMPLIFICATION>
                    <lod:EXEMPLE lod:MARQUE-USAGE="ALLG">
                      <lod:TEXTE-EX>
                        <lod:TEXTE>de Staat iwwerhëlt d'Käschten, déi aus dem Musée sengen Aktivitéite</lod:TEXTE>
                        <lod:ABREV-AD>r.</lod:ABREV-AD>
                      </lod:TEXTE-EX>
                    </lod:EXEMPLE>
                  </lod:EXEMPLIFICATION>
                  <lod:SYNONYMES>
                    <lod:SYN-PRESENTS>
                      <lod:TERME-SYN>sech erginn aus</lod:TERME-SYN>
                    </lod:SYN-PRESENTS>
                  </lod:SYNONYMES>
                </lod:UNITE-DE-SENS>
              </lod:PAS-DE-TRAD-SUBORDONNANTE>
            </lod:UNITE-TRAD>
          </lod:TRAITEMENT-LING-VRB>
        </lod:MS-TYPE-VRB>
      </lod:MICROSTRUCTURE>
    </lod:ARTICLE>
    <lod:FLX-VRB>
      <lod:INFINITIF>resultéieren</lod:INFINITIF>
      <lod:PART-PASS>resultéiert</lod:PART-PASS>
      <lod:INDICATIF>
        <lod:PRESENT>
          <lod:P3>resultéiert</lod:P3>
          <lod:P6>resultéieren</lod:P6>
        </lod:PRESENT>
        <lod:PASSE-COMPOSE>
          <lod:P3>huet resultéiert</lod:P3>
          <lod:P6>hu resultéiert</lod:P6>
        </lod:PASSE-COMPOSE>
        <lod:PLUS-QUE-PARFAIT>
          <lod:P3>hat resultéiert</lod:P3>
          <lod:P6>hate resultéiert</lod:P6>
        </lod:PLUS-QUE-PARFAIT>
      </lod:INDICATIF>
      <lod:CONDITIONNEL>
        <lod:PRESENT-COMPOSE>
          <lod:P3>géif resultéieren</lod:P3>
          <lod:P6>géife resultéieren</lod:P6>
        </lod:PRESENT-COMPOSE>
        <lod:PASSE-COMPOSE>
          <lod:P3>hätt resultéiert</lod:P3>
          <lod:P6>hätte resultéiert</lod:P6>
        </lod:PASSE-COMPOSE>
      </lod:CONDITIONNEL>
      <lod:IMPERATIF>
        <lod:PRESENT/>
      </lod:IMPERATIF>
    </lod:FLX-VRB>
  </lod:ITEM>
</lod:LOD>
