<?xml version="1.0" encoding="UTF-8"?>
<lod:LOD xmlns:lod="http://www.lod.lu/">
<lod:ITEM>
<lod:META lod:ID="SERIE1" />
<lod:ARTICLE>
<lod:ITEM-ADRESSE lod:ID-ITEM-ADRESSE="SERIE1ITE">Serie</lod:ITEM-ADRESSE>
<lod:MICROSTRUCTURE>
<lod:MS-TYPE-SUBST>
<lod:CAT-GRAM-SUBST />
<lod:GENRE lod:GEN="F" />
<lod:TYPE-SUBST>
<lod:SUBST-SIMPLE />
</lod:TYPE-SUBST>
<lod:PLURIEL>
<lod:TJ-NOMBRABLE>
<lod:FORME-PLURIEL lod:TYPE-PLURIEL="REGULIER">Serien</lod:FORME-PLURIEL>
</lod:TJ-NOMBRABLE>
</lod:PLURIEL>
<lod:TRAITEMENT-LING-SUBST>
<lod:TRADUCTION-DOMINANTE>
<lod:PAS-DE-TRAD-DOMIN />
</lod:TRADUCTION-DOMINANTE>
<lod:UNITE-TRAD>
<lod:PAS-DE-TRAD-SUBORDONNANTE>
<lod:UNITE-DE-SENS lod:ID-UNITE-DE-SENS="SERIE1UNI1">
<lod:DOM-SPEC />
<lod:MARQUE-USAGE />
<lod:EQUIV-TRAD-ALL>
<lod:ETA-EXPLICITE lod:FONCTION-ETA="EQUIVALENT">Serie</lod:ETA-EXPLICITE>
<lod:RS-ETA-ABSENTE />
<lod:ETA-EXPLICITE lod:FONCTION-ETA="EQUIVALENT">Reihe</lod:ETA-EXPLICITE>
<lod:RS-ETA-PRESENTE>von Gegenst&#228;nden</lod:RS-ETA-PRESENTE>
</lod:EQUIV-TRAD-ALL>
<lod:EQUIV-TRAD-FR>
<lod:ETF-EXPLICITE lod:FONCTION-ETF="EQUIVALENT">s&#233;rie</lod:ETF-EXPLICITE>
<lod:RS-ETF-PRESENTE>d'objets</lod:RS-ETF-PRESENTE>
</lod:EQUIV-TRAD-FR>
<lod:EQUIV-TRAD-EN>
<lod:ETE-EXPLICITE lod:FONCTION-ETE="EQUIVALENT">series</lod:ETE-EXPLICITE>
<lod:RS-ETE-PRESENTE>of objects</lod:RS-ETE-PRESENTE>
</lod:EQUIV-TRAD-EN>
<lod:EQUIV-TRAD-PO>
<lod:ETP-EXPLICITE lod:FONCTION-ETP="EQUIVALENT">s&#233;rie</lod:ETP-EXPLICITE>
<lod:RS-ETP-PRESENTE>de objetos</lod:RS-ETP-PRESENTE>
</lod:EQUIV-TRAD-PO>
<lod:EXEMPLIFICATION>
<lod:EXEMPLE lod:MARQUE-USAGE="ALLG">
<lod:TEXTE-EX>
<lod:TEXTE>d'L&#235;tzebuerger Post g&#235;tt eng nei</lod:TEXTE>
<lod:ABREV-AD>S.</lod:ABREV-AD>
<lod:TEXTE>Timberen eraus</lod:TEXTE>
</lod:TEXTE-EX>
</lod:EXEMPLE>
<lod:EXEMPLE>
<lod:TEXTE-EX>
<lod:TEXTE>lorem ipsum dolor sit amet,</lod:TEXTE>
<lod:ABREV-AD>Serie</lod:ABREV-AD>
<lod:TEXTE>consectetur adipiscing elit</lod:TEXTE>
</lod:TEXTE-EX>
</lod:EXEMPLE>
</lod:EXEMPLIFICATION>
<lod:SYNONYMES>
<lod:SYN-ABSENTS />
</lod:SYNONYMES>
</lod:UNITE-DE-SENS>
</lod:PAS-DE-TRAD-SUBORDONNANTE>
</lod:UNITE-TRAD>
<lod:UNITE-TRAD>
<lod:PAS-DE-TRAD-SUBORDONNANTE>
<lod:UNITE-DE-SENS lod:ID-UNITE-DE-SENS="SERIE1UNI3">
<lod:DOM-SPEC />
<lod:MARQUE-USAGE />
<lod:EQUIV-TRAD-ALL>
<lod:ETA-EXPLICITE lod:FONCTION-ETA="EQUIVALENT">Serie</lod:ETA-EXPLICITE>
<lod:RS-ETA-PRESENTE>Sendereihe, Artikelreihe</lod:RS-ETA-PRESENTE>
</lod:EQUIV-TRAD-ALL>
<lod:EQUIV-TRAD-FR>
<lod:ETF-EXPLICITE lod:FONCTION-ETF="EQUIVALENT">s&#233;rie</lod:ETF-EXPLICITE>
<lod:RS-ETF-PRESENTE>d'&#233;missions, d'articles</lod:RS-ETF-PRESENTE>
</lod:EQUIV-TRAD-FR>
<lod:EQUIV-TRAD-EN>
<lod:ETE-EXPLICITE lod:FONCTION-ETE="EQUIVALENT">series</lod:ETE-EXPLICITE>
<lod:RS-ETE-PRESENTE>broadcasting, publishing</lod:RS-ETE-PRESENTE>
</lod:EQUIV-TRAD-EN>
<lod:EQUIV-TRAD-PO>
<lod:ETP-EXPLICITE lod:FONCTION-ETP="EQUIVALENT">s&#233;rie</lod:ETP-EXPLICITE>
<lod:RS-ETP-PRESENTE>de emiss&#245;es, de artigos</lod:RS-ETP-PRESENTE>
</lod:EQUIV-TRAD-PO>
<lod:EXEMPLIFICATION>
<lod:EXEMPLE>
<lod:TEXTE-EX>
<lod:TEXTE>lorem ipsum dolor sit amet,</lod:TEXTE>
<lod:ABREV-AD>Serie</lod:ABREV-AD>
<lod:TEXTE>consectetur adipiscing elit</lod:TEXTE>
</lod:TEXTE-EX>
</lod:EXEMPLE>
<lod:EXEMPLE>
<lod:TEXTE-EX>
<lod:TEXTE>lorem ipsum dolor sit amet,</lod:TEXTE>
<lod:ABREV-AD>Serie</lod:ABREV-AD>
<lod:TEXTE>consectetur adipiscing elit</lod:TEXTE>
</lod:TEXTE-EX>
</lod:EXEMPLE>
<lod:EXEMPLE>
<lod:TEXTE-EX>
<lod:TEXTE>lorem ipsum dolor sit amet,</lod:TEXTE>
<lod:ABREV-AD>Serie</lod:ABREV-AD>
<lod:TEXTE>consectetur adipiscing elit</lod:TEXTE>
</lod:TEXTE-EX>
</lod:EXEMPLE>
</lod:EXEMPLIFICATION>
<lod:SYNONYMES>
<lod:SYN-ABSENTS />
</lod:SYNONYMES>
</lod:UNITE-DE-SENS>
</lod:PAS-DE-TRAD-SUBORDONNANTE>
</lod:UNITE-TRAD>
<lod:UNITE-TRAD>
<lod:PAS-DE-TRAD-SUBORDONNANTE>
<lod:UNITE-DE-SENS lod:ID-UNITE-DE-SENS="SERIE1UNI4">
<lod:DOM-SPEC />
<lod:MARQUE-USAGE />
<lod:UNITE-POLYLEX-LUX>eng (ganz) Serie (vun)</lod:UNITE-POLYLEX-LUX>
<lod:EQUIV-TRAD-ALL>
<lod:ETA-EXPLICITE lod:FONCTION-ETA="EQUIVALENT">eine (ganze) Reihe (von)</lod:ETA-EXPLICITE>
<lod:RS-ETA-ABSENTE />
<lod:ETA-EXPLICITE lod:FONCTION-ETA="EQUIVALENT">eine Anzahl (von)</lod:ETA-EXPLICITE>
<lod:RS-ETA-ABSENTE />
</lod:EQUIV-TRAD-ALL>
<lod:EQUIV-TRAD-FR>
<lod:ETF-EXPLICITE lod:FONCTION-ETF="EQUIVALENT">un certain nombre de</lod:ETF-EXPLICITE>
<lod:RS-ETF-ABSENTE />
<lod:ETF-EXPLICITE lod:FONCTION-ETF="EQUIVALENT">un grand nombre de</lod:ETF-EXPLICITE>
<lod:RS-ETF-ABSENTE />
</lod:EQUIV-TRAD-FR>
<lod:EQUIV-TRAD-EN>
<lod:ETE-EXPLICITE lod:FONCTION-ETE="EQUIVALENT">a (whole) series (of)</lod:ETE-EXPLICITE>
</lod:EQUIV-TRAD-EN>
<lod:EQUIV-TRAD-PO>
<lod:ETP-EXPLICITE lod:FONCTION-ETP="EQUIVALENT">uma s&#233;rie de</lod:ETP-EXPLICITE>
<lod:ETP-EXPLICITE lod:FONCTION-ETP="EQUIVALENT">um grande n&#250;mero de</lod:ETP-EXPLICITE>
</lod:EQUIV-TRAD-PO>
<lod:EXEMPLIFICATION>
<lod:EXEMPLE>
<lod:TEXTE-EX>
<lod:TEXTE>lorem ipsum dolor sit amet,</lod:TEXTE>
<lod:ABREV-AD>Serie</lod:ABREV-AD>
<lod:TEXTE>consectetur adipiscing elit</lod:TEXTE>
</lod:TEXTE-EX>
</lod:EXEMPLE>
<lod:EXEMPLE>
<lod:TEXTE-EX>
<lod:TEXTE>lorem ipsum dolor sit amet,</lod:TEXTE>
<lod:ABREV-AD>Serie</lod:ABREV-AD>
<lod:TEXTE>consectetur adipiscing elit</lod:TEXTE>
</lod:TEXTE-EX>
</lod:EXEMPLE>
<lod:EXEMPLE lod:MARQUE-USAGE="ALLG">
<lod:TEXTE-EX>
<lod:TEXTE>wann s de al Postkaarte brauchs, ech hunn eng ganz</lod:TEXTE>
<lod:ABREV-AD>S.</lod:ABREV-AD>
<lod:TEXTE>doheem</lod:TEXTE>
</lod:TEXTE-EX>
</lod:EXEMPLE>
</lod:EXEMPLIFICATION>
<lod:SYNONYMES>
<lod:SYN-PRESENTS>
<lod:TERME-SYN>eng (ganz) Rei (vun)</lod:TERME-SYN>
<lod:TERME-SYN>eng (ganz) R&#235;tsch (vun)</lod:TERME-SYN>
</lod:SYN-PRESENTS>
</lod:SYNONYMES>
</lod:UNITE-DE-SENS>
</lod:PAS-DE-TRAD-SUBORDONNANTE>
</lod:UNITE-TRAD>
</lod:TRAITEMENT-LING-SUBST>
</lod:MS-TYPE-SUBST>
</lod:MICROSTRUCTURE>
</lod:ARTICLE>
</lod:ITEM>
</lod:LOD>