<?xml version="1.0" encoding="UTF-8"?>
<lod:LOD xmlns:lod="http://www.lod.lu/">
  <lod:ITEM>
    <lod:META lod:ID="SIMULEIEREN1"/>
    <lod:ARTICLE>
      <lod:ITEM-ADRESSE lod:ID-ITEM-ADRESSE="SIMULEIEREN1ITE">simuléieren</lod:ITEM-ADRESSE>
      <lod:MICROSTRUCTURE>
        <lod:MS-TYPE-VRB>
          <lod:CAT-GRAM-VRB/>
          <lod:VRB-AUXILIAIRE lod:AUXIL="HUNN"/>
          <lod:PARTICIPE-PASSE>simuléiert</lod:PARTICIPE-PASSE>
          <lod:TRAITEMENT-LING-VRB>
            <lod:REFLEX-PRONOM lod:REFPRON="TRANSITIF"/>
            <lod:EMPLOI-IMPERS lod:EMPLOI-IMPERS="VRB-EMPL-IMPERS-IMPOSS"/>
            <lod:TRADUCTION-DOMINANTE>
              <lod:PAS-DE-TRAD-DOMIN/>
            </lod:TRADUCTION-DOMINANTE>
            <lod:UNITE-TRAD>
              <lod:PAS-DE-TRAD-SUBORDONNANTE>
                <lod:UNITE-DE-SENS lod:ID-UNITE-DE-SENS="SIMULEIEREN1UNI1">
                  <lod:DOM-SPEC/>
                  <lod:MARQUE-USAGE/>
                  <lod:EQUIV-TRAD-ALL>
                    <lod:ETA-EXPLICITE lod:FONCTION-ETA="EQUIVALENT">simulieren</lod:ETA-EXPLICITE>
                    <lod:RS-ETA-PRESENTE>vortäuschen</lod:RS-ETA-PRESENTE>
                  </lod:EQUIV-TRAD-ALL>
                  <lod:EQUIV-TRAD-FR>
                    <lod:ETF-EXPLICITE lod:FONCTION-ETF="EQUIVALENT">simuler</lod:ETF-EXPLICITE>
                    <lod:RS-ETF-PRESENTE>feindre</lod:RS-ETF-PRESENTE>
                  </lod:EQUIV-TRAD-FR>
                  <lod:EQUIV-TRAD-EN>
                    <lod:ETE-EXPLICITE lod:FONCTION-ETE="EQUIVALENT">to feign</lod:ETE-EXPLICITE>
                    <lod:ETE-EXPLICITE lod:FONCTION-ETE="EQUIVALENT">to pretend</lod:ETE-EXPLICITE>
                    <lod:ETE-EXPLICITE lod:FONCTION-ETE="EQUIVALENT">to fake</lod:ETE-EXPLICITE>
                  </lod:EQUIV-TRAD-EN>
                  <lod:EQUIV-TRAD-PO>
                    <lod:ETP-EXPLICITE lod:FONCTION-ETP="EQUIVALENT">simular</lod:ETP-EXPLICITE>
                    <lod:RS-ETP-PRESENTE>fingir</lod:RS-ETP-PRESENTE>
                  </lod:EQUIV-TRAD-PO>
                  <lod:EXEMPLIFICATION>
                    <lod:EXEMPLE lod:MARQUE-USAGE="ALLG">
                      <lod:TEXTE-EX>
                        <lod:TEXTE>als Kand</lod:TEXTE>
                        <lod:ABREV-AD>hunn</lod:ABREV-AD>
                        <lod:TEXTE>ech heiansdo Bauchwéi</lod:TEXTE>
                        <lod:ABREV-AD>simuléiert</lod:ABREV-AD>
                        <lod:TEXTE>, wann ech net wollt an d'Schoul goen</lod:TEXTE>
                      </lod:TEXTE-EX>
                    </lod:EXEMPLE>
                  </lod:EXEMPLIFICATION>
                  <lod:SYNONYMES>
                    <lod:SYN-PRESENTS>
                      <lod:TERME-SYN>virtäuschen</lod:TERME-SYN>
                    </lod:SYN-PRESENTS>
                  </lod:SYNONYMES>
                </lod:UNITE-DE-SENS>
              </lod:PAS-DE-TRAD-SUBORDONNANTE>
            </lod:UNITE-TRAD>
            <lod:UNITE-TRAD>
              <lod:PAS-DE-TRAD-SUBORDONNANTE>
                <lod:UNITE-DE-SENS lod:ID-UNITE-DE-SENS="SIMULEIEREN1UNI2">
                  <lod:DOM-SPEC/>
                  <lod:MARQUE-USAGE/>
                  <lod:EQUIV-TRAD-ALL>
                    <lod:ETA-EXPLICITE lod:FONCTION-ETA="EQUIVALENT">simulieren</lod:ETA-EXPLICITE>
                    <lod:RS-ETA-PRESENTE>nachstellen, nachbilden</lod:RS-ETA-PRESENTE>
                  </lod:EQUIV-TRAD-ALL>
                  <lod:EQUIV-TRAD-FR>
                    <lod:ETF-EXPLICITE lod:FONCTION-ETF="EQUIVALENT">simuler</lod:ETF-EXPLICITE>
                    <lod:RS-ETF-PRESENTE>représenter</lod:RS-ETF-PRESENTE>
                  </lod:EQUIV-TRAD-FR>
                  <lod:EQUIV-TRAD-EN>
                    <lod:ETE-EXPLICITE lod:FONCTION-ETE="EQUIVALENT">to simulate</lod:ETE-EXPLICITE>
                    <lod:RS-ETE-PRESENTE>crisis conditions</lod:RS-ETE-PRESENTE>
                    <lod:ETE-EXPLICITE lod:FONCTION-ETE="EQUIVALENT">to undertake a simulated exercise</lod:ETE-EXPLICITE>
                  </lod:EQUIV-TRAD-EN>
                  <lod:EQUIV-TRAD-PO>
                    <lod:ETP-EXPLICITE lod:FONCTION-ETP="EQUIVALENT">simular</lod:ETP-EXPLICITE>
                    <lod:RS-ETP-PRESENTE>representar</lod:RS-ETP-PRESENTE>
                  </lod:EQUIV-TRAD-PO>
                  <lod:EXEMPLIFICATION>
                    <lod:EXEMPLE lod:MARQUE-USAGE="ALLG">
                      <lod:TEXTE-EX>
                        <lod:TEXTE>de Mëtteg</lod:TEXTE>
                        <lod:ABREV-AD>s.</lod:ABREV-AD>
                        <lod:TEXTE>d'Pompjeeën e Katastrophenasaz</lod:TEXTE>
                      </lod:TEXTE-EX>
                    </lod:EXEMPLE>
                    <lod:EXEMPLE lod:MARQUE-USAGE="ALLG">
                      <lod:TEXTE-EX>
                        <lod:TEXTE>d'Physiker</lod:TEXTE>
                        <lod:ABREV-AD>hunn</lod:ABREV-AD>
                        <lod:TEXTE>d'Kettereaktioun um Computer</lod:TEXTE>
                        <lod:ABREV-AD>simuléiert</lod:ABREV-AD>
                      </lod:TEXTE-EX>
                    </lod:EXEMPLE>
                  </lod:EXEMPLIFICATION>
                  <lod:SYNONYMES>
                    <lod:SYN-ABSENTS/>
                  </lod:SYNONYMES>
                </lod:UNITE-DE-SENS>
              </lod:PAS-DE-TRAD-SUBORDONNANTE>
            </lod:UNITE-TRAD>
          </lod:TRAITEMENT-LING-VRB>
          <lod:TRAITEMENT-LING-VRB>
            <lod:REFLEX-PRONOM lod:REFPRON="INTRANSITIF"/>
            <lod:EMPLOI-IMPERS lod:EMPLOI-IMPERS="VRB-EMPL-IMPERS-IMPOSS"/>
            <lod:TRADUCTION-DOMINANTE>
              <lod:PAS-DE-TRAD-DOMIN/>
            </lod:TRADUCTION-DOMINANTE>
            <lod:UNITE-TRAD>
              <lod:PAS-DE-TRAD-SUBORDONNANTE>
                <lod:UNITE-DE-SENS lod:ID-UNITE-DE-SENS="SIMULEIEREN1UNI4">
                  <lod:DOM-SPEC/>
                  <lod:MARQUE-USAGE/>
                  <lod:EQUIV-TRAD-ALL>
                    <lod:ETA-EXPLICITE lod:FONCTION-ETA="EQUIVALENT">simulieren</lod:ETA-EXPLICITE>
                    <lod:RS-ETA-ABSENTE/>
                  </lod:EQUIV-TRAD-ALL>
                  <lod:EQUIV-TRAD-FR>
                    <lod:ETF-EXPLICITE lod:FONCTION-ETF="EQUIVALENT">simuler</lod:ETF-EXPLICITE>
                    <lod:RS-ETF-ABSENTE/>
                  </lod:EQUIV-TRAD-FR>
                  <lod:EQUIV-TRAD-EN>
                    <lod:ETE-EXPLICITE lod:FONCTION-ETE="EQUIVALENT">to pretend</lod:ETE-EXPLICITE>
                    <lod:ETE-EXPLICITE lod:FONCTION-ETE="EQUIVALENT">to fake</lod:ETE-EXPLICITE>
                  </lod:EQUIV-TRAD-EN>
                  <lod:EQUIV-TRAD-PO>
                    <lod:ETP-EXPLICITE lod:FONCTION-ETP="EQUIVALENT">simular</lod:ETP-EXPLICITE>
                  </lod:EQUIV-TRAD-PO>
                  <lod:EXEMPLIFICATION>
                    <lod:EXEMPLE lod:MARQUE-USAGE="ALLG">
                      <lod:TEXTE-EX>
                        <lod:TEXTE>dem Patient feelt näischt, e</lod:TEXTE>
                        <lod:ABREV-AD>simuléiert</lod:ABREV-AD>
                        <lod:TEXTE>just</lod:TEXTE>
                      </lod:TEXTE-EX>
                    </lod:EXEMPLE>
                  </lod:EXEMPLIFICATION>
                  <lod:SYNONYMES>
                    <lod:SYN-PRESENTS>
                      <lod:TERME-SYN>sech (esou) maachen</lod:TERME-SYN>
                    </lod:SYN-PRESENTS>
                  </lod:SYNONYMES>
                </lod:UNITE-DE-SENS>
              </lod:PAS-DE-TRAD-SUBORDONNANTE>
            </lod:UNITE-TRAD>
          </lod:TRAITEMENT-LING-VRB>
        </lod:MS-TYPE-VRB>
      </lod:MICROSTRUCTURE>
    </lod:ARTICLE>
    <lod:FLX-VRB>
      <lod:INFINITIF>simuléieren</lod:INFINITIF>
      <lod:PART-PASS>simuléiert</lod:PART-PASS>
      <lod:INDICATIF>
        <lod:PRESENT>
          <lod:P1>simuléieren</lod:P1>
          <lod:P2>simuléiers</lod:P2>
          <lod:P3>simuléiert</lod:P3>
          <lod:P4>simuléieren</lod:P4>
          <lod:P5>simuléiert</lod:P5>
          <lod:P6>simuléieren</lod:P6>
        </lod:PRESENT>
        <lod:PASSE-COMPOSE>
          <lod:P1>hu simuléiert</lod:P1>
          <lod:P2>hues simuléiert</lod:P2>
          <lod:P3>huet simuléiert</lod:P3>
          <lod:P4>hu simuléiert</lod:P4>
          <lod:P5>hutt simuléiert</lod:P5>
          <lod:P6>hu simuléiert</lod:P6>
        </lod:PASSE-COMPOSE>
        <lod:PLUS-QUE-PARFAIT>
          <lod:P1>hat simuléiert</lod:P1>
          <lod:P2>has simuléiert</lod:P2>
          <lod:P3>hat simuléiert</lod:P3>
          <lod:P4>hate simuléiert</lod:P4>
          <lod:P5>hat simuléiert</lod:P5>
          <lod:P6>hate simuléiert</lod:P6>
        </lod:PLUS-QUE-PARFAIT>
      </lod:INDICATIF>
      <lod:CONDITIONNEL>
        <lod:PRESENT-COMPOSE>
          <lod:P1>géif simuléieren</lod:P1>
          <lod:P2>géifs simuléieren</lod:P2>
          <lod:P3>géif simuléieren</lod:P3>
          <lod:P4>géife simuléieren</lod:P4>
          <lod:P5>géift simuléieren</lod:P5>
          <lod:P6>géife simuléieren</lod:P6>
        </lod:PRESENT-COMPOSE>
        <lod:PASSE-COMPOSE>
          <lod:P1>hätt simuléiert</lod:P1>
          <lod:P2>häss simuléiert</lod:P2>
          <lod:P3>hätt simuléiert</lod:P3>
          <lod:P4>hätte simuléiert</lod:P4>
          <lod:P5>hätt simuléiert</lod:P5>
          <lod:P6>hätte simuléiert</lod:P6>
        </lod:PASSE-COMPOSE>
      </lod:CONDITIONNEL>
      <lod:IMPERATIF>
        <lod:PRESENT>
          <lod:P2>simuléier!</lod:P2>
          <lod:P5>simuléiert!</lod:P5>
        </lod:PRESENT>
      </lod:IMPERATIF>
    </lod:FLX-VRB>
  </lod:ITEM>
</lod:LOD>
