<?xml version="1.0" encoding="UTF-8"?>
<lod:LOD xmlns:lod="http://www.lod.lu/">
  <lod:ITEM>
    <lod:META lod:ID="STANZEN1"/>
    <lod:ARTICLE>
      <lod:ITEM-ADRESSE lod:ID-ITEM-ADRESSE="STANZEN1ITE">stanzen</lod:ITEM-ADRESSE>
      <lod:MICROSTRUCTURE>
        <lod:MS-TYPE-VRB>
          <lod:CAT-GRAM-VRB/>
          <lod:VRB-AUXILIAIRE lod:AUXIL="HUNN"/>
          <lod:PARTICIPE-PASSE>gestanzt</lod:PARTICIPE-PASSE>
          <lod:TRAITEMENT-LING-VRB>
            <lod:REFLEX-PRONOM lod:REFPRON="TRANSITIF"/>
            <lod:EMPLOI-IMPERS lod:EMPLOI-IMPERS="VRB-EMPL-IMPERS-IMPOSS"/>
            <lod:TRADUCTION-DOMINANTE>
              <lod:PAS-DE-TRAD-DOMIN/>
            </lod:TRADUCTION-DOMINANTE>
            <lod:UNITE-TRAD>
              <lod:PAS-DE-TRAD-SUBORDONNANTE>
                <lod:UNITE-DE-SENS lod:ID-UNITE-DE-SENS="STANZEN1UNI1">
                  <lod:DOM-SPEC/>
                  <lod:MARQUE-USAGE/>
                  <lod:EQUIV-TRAD-ALL>
                    <lod:ETA-EXPLICITE lod:FONCTION-ETA="EQUIVALENT">stanzen</lod:ETA-EXPLICITE>
                    <lod:RS-ETA-ABSENTE/>
                    <lod:ETA-EXPLICITE lod:FONCTION-ETA="EQUIVALENT">stanzen</lod:ETA-EXPLICITE>
                    <lod:RS-ETA-ABSENTE/>
                    <lod:ETA-EXPLICITE lod:FONCTION-ETA="EQUIVALENT">ausstanzen</lod:ETA-EXPLICITE>
                    <lod:RS-ETA-ABSENTE/>
                  </lod:EQUIV-TRAD-ALL>
                  <lod:EQUIV-TRAD-FR>
                    <lod:ETF-EXPLICITE lod:FONCTION-ETF="EQUIVALENT">poinçonner</lod:ETF-EXPLICITE>
                    <lod:RS-ETF-PRESENTE>découper</lod:RS-ETF-PRESENTE>
                  </lod:EQUIV-TRAD-FR>
                  <lod:EQUIV-TRAD-EN>
                    <lod:ETE-EXPLICITE lod:FONCTION-ETE="EQUIVALENT">to punch</lod:ETE-EXPLICITE>
                    <lod:RS-ETE-PRESENTE>a hole</lod:RS-ETE-PRESENTE>
                  </lod:EQUIV-TRAD-EN>
                  <lod:EQUIV-TRAD-PO>
                    <lod:ETP-EXPLICITE lod:FONCTION-ETP="EQUIVALENT">furar</lod:ETP-EXPLICITE>
                    <lod:ETP-EXPLICITE lod:FONCTION-ETP="EQUIVALENT">puncionar</lod:ETP-EXPLICITE>
                  </lod:EQUIV-TRAD-PO>
                  <lod:EXEMPLIFICATION>
                    <lod:EXEMPLE lod:MARQUE-USAGE="ALLG">
                      <lod:TEXTE-EX>
                        <lod:TEXTE>déi dote Maschinn</lod:TEXTE>
                        <lod:ABREV-AD>stanzt</lod:ABREV-AD>
                        <lod:TEXTE>Lächer an de Blech</lod:TEXTE>
                      </lod:TEXTE-EX>
                    </lod:EXEMPLE>
                  </lod:EXEMPLIFICATION>
                  <lod:SYNONYMES>
                    <lod:SYN-ABSENTS/>
                  </lod:SYNONYMES>
                </lod:UNITE-DE-SENS>
              </lod:PAS-DE-TRAD-SUBORDONNANTE>
            </lod:UNITE-TRAD>
            <lod:UNITE-TRAD>
              <lod:PAS-DE-TRAD-SUBORDONNANTE>
                <lod:UNITE-DE-SENS lod:ID-UNITE-DE-SENS="STANZEN1UNI2">
                  <lod:DOM-SPEC/>
                  <lod:MARQUE-USAGE/>
                  <lod:EQUIV-TRAD-ALL>
                    <lod:ETA-EXPLICITE lod:FONCTION-ETA="EQUIVALENT">stanzen</lod:ETA-EXPLICITE>
                    <lod:RS-ETA-PRESENTE>prägen</lod:RS-ETA-PRESENTE>
                  </lod:EQUIV-TRAD-ALL>
                  <lod:EQUIV-TRAD-FR>
                    <lod:ETF-EXPLICITE lod:FONCTION-ETF="EQUIVALENT">estamper</lod:ETF-EXPLICITE>
                    <lod:RS-ETF-ABSENTE/>
                    <lod:ETF-EXPLICITE lod:FONCTION-ETF="EQUIVALENT">frapper</lod:ETF-EXPLICITE>
                    <lod:RS-ETF-ABSENTE/>
                  </lod:EQUIV-TRAD-FR>
                  <lod:EQUIV-TRAD-EN>
                    <lod:ETE-EXPLICITE lod:FONCTION-ETE="EQUIVALENT">to emboss</lod:ETE-EXPLICITE>
                    <lod:ETE-EXPLICITE lod:FONCTION-ETE="EQUIVALENT">to stamp</lod:ETE-EXPLICITE>
                  </lod:EQUIV-TRAD-EN>
                  <lod:EQUIV-TRAD-PO>
                    <lod:ETP-EXPLICITE lod:FONCTION-ETP="EQUIVALENT">cunhar</lod:ETP-EXPLICITE>
                    <lod:ETP-EXPLICITE lod:FONCTION-ETP="EQUIVALENT">estampar</lod:ETP-EXPLICITE>
                  </lod:EQUIV-TRAD-PO>
                  <lod:EXEMPLIFICATION>
                    <lod:EXEMPLE lod:MARQUE-USAGE="ALLG">
                      <lod:TEXTE-EX>
                        <lod:TEXTE>zanter dem 19. Joerhonnert</lod:TEXTE>
                        <lod:ABREV-AD>gouf</lod:ABREV-AD>
                        <lod:TEXTE>an där Regioun op all Mënz e spezielle Wope</lod:TEXTE>
                        <lod:ABREV-AD>gestanzt</lod:ABREV-AD>
                      </lod:TEXTE-EX>
                    </lod:EXEMPLE>
                    <lod:EXEMPLE lod:MARQUE-USAGE="ALLG">
                      <lod:TEXTE-EX>
                        <lod:TEXTE>ech hu meng Initialen an den Deckel vum Buch</lod:TEXTE>
                        <lod:ABREV-AD>stanze</lod:ABREV-AD>
                        <lod:TEXTE>gelooss</lod:TEXTE>
                      </lod:TEXTE-EX>
                    </lod:EXEMPLE>
                  </lod:EXEMPLIFICATION>
                  <lod:SYNONYMES>
                    <lod:SYN-ABSENTS/>
                  </lod:SYNONYMES>
                </lod:UNITE-DE-SENS>
              </lod:PAS-DE-TRAD-SUBORDONNANTE>
            </lod:UNITE-TRAD>
          </lod:TRAITEMENT-LING-VRB>
        </lod:MS-TYPE-VRB>
      </lod:MICROSTRUCTURE>
    </lod:ARTICLE>
    <lod:FLX-VRB>
      <lod:INFINITIF>stanzen</lod:INFINITIF>
      <lod:PART-PASS>gestanzt</lod:PART-PASS>
      <lod:INDICATIF>
        <lod:PRESENT>
          <lod:P1>stanzen</lod:P1>
          <lod:P2>stanz</lod:P2>
          <lod:P3>stanzt</lod:P3>
          <lod:P4>stanzen</lod:P4>
          <lod:P5>stanzt</lod:P5>
          <lod:P6>stanzen</lod:P6>
        </lod:PRESENT>
        <lod:PASSE-COMPOSE>
          <lod:P1>hu gestanzt</lod:P1>
          <lod:P2>hues gestanzt</lod:P2>
          <lod:P3>huet gestanzt</lod:P3>
          <lod:P4>hu gestanzt</lod:P4>
          <lod:P5>hutt gestanzt</lod:P5>
          <lod:P6>hu gestanzt</lod:P6>
        </lod:PASSE-COMPOSE>
        <lod:PLUS-QUE-PARFAIT>
          <lod:P1>hat gestanzt</lod:P1>
          <lod:P2>has gestanzt</lod:P2>
          <lod:P3>hat gestanzt</lod:P3>
          <lod:P4>hate gestanzt</lod:P4>
          <lod:P5>hat gestanzt</lod:P5>
          <lod:P6>hate gestanzt</lod:P6>
        </lod:PLUS-QUE-PARFAIT>
      </lod:INDICATIF>
      <lod:CONDITIONNEL>
        <lod:PRESENT-COMPOSE>
          <lod:P1>géif stanzen</lod:P1>
          <lod:P2>géifs stanzen</lod:P2>
          <lod:P3>géif stanzen</lod:P3>
          <lod:P4>géife stanzen</lod:P4>
          <lod:P5>géift stanzen</lod:P5>
          <lod:P6>géife stanzen</lod:P6>
        </lod:PRESENT-COMPOSE>
        <lod:PASSE-COMPOSE>
          <lod:P1>hätt gestanzt</lod:P1>
          <lod:P2>häss gestanzt</lod:P2>
          <lod:P3>hätt gestanzt</lod:P3>
          <lod:P4>hätte gestanzt</lod:P4>
          <lod:P5>hätt gestanzt</lod:P5>
          <lod:P6>hätte gestanzt</lod:P6>
        </lod:PASSE-COMPOSE>
      </lod:CONDITIONNEL>
      <lod:IMPERATIF>
        <lod:PRESENT>
          <lod:P2>stanz!</lod:P2>
          <lod:P5>stanzt!</lod:P5>
        </lod:PRESENT>
      </lod:IMPERATIF>
    </lod:FLX-VRB>
  </lod:ITEM>
</lod:LOD>
