<?xml version="1.0" encoding="UTF-8"?>
<lod:LOD xmlns:lod="http://www.lod.lu/">
  <lod:ITEM>
    <lod:META lod:ID="VERZEILECH1"/>
    <lod:ARTICLE>
      <lod:ITEM-ADRESSE lod:ID-ITEM-ADRESSE="VERZEILECH1ITE">verzeilech</lod:ITEM-ADRESSE>
      <lod:MICROSTRUCTURE>
        <lod:MS-TYPE-ADJ>
          <lod:CAT-GRAM-ADJ/>
          <lod:TRAITEMENT-LING-ADJ>
            <lod:TRADUCTION-DOMINANTE>
              <lod:PAS-DE-TRAD-DOMIN/>
            </lod:TRADUCTION-DOMINANTE>
            <lod:UNITE-TRAD>
              <lod:PAS-DE-TRAD-SUBORDONNANTE>
                <lod:UNITE-DE-SENS lod:ID-UNITE-DE-SENS="VERZEILECH1UNI1">
                  <lod:DOM-SPEC/>
                  <lod:MARQUE-USAGE/>
                  <lod:EQUIV-TRAD-ALL>
                    <lod:ETA-EXPLICITE lod:FONCTION-ETA="EQUIVALENT">verzeihlich</lod:ETA-EXPLICITE>
                    <lod:RS-ETA-ABSENTE/>
                  </lod:EQUIV-TRAD-ALL>
                  <lod:EQUIV-TRAD-FR>
                    <lod:ETF-EXPLICITE lod:FONCTION-ETF="EQUIVALENT">pardonnable</lod:ETF-EXPLICITE>
                    <lod:RS-ETF-ABSENTE/>
                  </lod:EQUIV-TRAD-FR>
                  <lod:EQUIV-TRAD-EN>
                    <lod:ETE-EXPLICITE lod:FONCTION-ETE="EQUIVALENT">forgivable</lod:ETE-EXPLICITE>
                  </lod:EQUIV-TRAD-EN>
                  <lod:EQUIV-TRAD-PO>
                    <lod:ETP-EXPLICITE lod:FONCTION-ETP="EQUIVALENT">perdoável</lod:ETP-EXPLICITE>
                  </lod:EQUIV-TRAD-PO>
                  <lod:EXEMPLIFICATION>
                    <lod:EXEMPLE lod:MARQUE-USAGE="ALLG">
                      <lod:TEXTE-EX>
                        <lod:TEXTE>ech sinn net béis mat dir, dat war e</lod:TEXTE>
                        <lod:ABREV-AD>v.e</lod:ABREV-AD>
                        <lod:TEXTE>Feeler</lod:TEXTE>
                      </lod:TEXTE-EX>
                    </lod:EXEMPLE>
                  </lod:EXEMPLIFICATION>
                  <lod:SYNONYMES>
                    <lod:SYN-ABSENTS/>
                  </lod:SYNONYMES>
                </lod:UNITE-DE-SENS>
              </lod:PAS-DE-TRAD-SUBORDONNANTE>
            </lod:UNITE-TRAD>
          </lod:TRAITEMENT-LING-ADJ>
        </lod:MS-TYPE-ADJ>
      </lod:MICROSTRUCTURE>
    </lod:ARTICLE>
    <lod:FLX-ADJ>
      <lod:GRONDFORMEN>
        <lod:POSITIV>verzeilech</lod:POSITIV>
      </lod:GRONDFORMEN>
      <lod:DEKL>
        <lod:POSITIV>
          <lod:SINGULIER>
            <lod:M>
              <lod:NOM>verzeilechen</lod:NOM>
              <lod:AKK>verzeilechen</lod:AKK>
              <lod:DAT>verzeilechen</lod:DAT>
              <lod:GEN>verzeilechen</lod:GEN>
            </lod:M>
            <lod:W>
              <lod:NOM>verzeilech</lod:NOM>
              <lod:AKK>verzeilech</lod:AKK>
              <lod:DAT>verzeilecher</lod:DAT>
              <lod:GEN>verzeilecher</lod:GEN>
            </lod:W>
            <lod:S>
              <lod:NOM>verzeilecht</lod:NOM>
              <lod:AKK>verzeilecht</lod:AKK>
              <lod:DAT>verzeilechen</lod:DAT>
              <lod:GEN>verzeilechen</lod:GEN>
            </lod:S>
          </lod:SINGULIER>
          <lod:PLURIEL>
            <lod:MWS>
              <lod:NOM>verzeilech</lod:NOM>
              <lod:AKK>verzeilech</lod:AKK>
              <lod:DAT>verzeilechen</lod:DAT>
              <lod:GEN>verzeilecher</lod:GEN>
            </lod:MWS>
          </lod:PLURIEL>
        </lod:POSITIV>
      </lod:DEKL>
    </lod:FLX-ADJ>
  </lod:ITEM>
</lod:LOD>
